{
  "name": "保险条款变更应遵循合同自治原则，法院不能强制变更",
  "children": [
    {
      "name": "基本資訊",
      "children": [
        {
          "name": "案號：北京铁路运输法院（2016）京7101民初字第20号民事判决书"
        },
        {
          "name": "案由：人身保险合同纠纷"
        }
      ]
    },
    {
      "name": "案情摘要",
      "children": [
        {
          "name": "原告张宇澄因保单贷款利率问题起诉新华人寿保险公司，原因是央行不再公布五年定期存款利率，导致保险合同中约定的利率条款无法履行。"
        },
        {
          "name": "法院判决驳回原告诉讼请求，认为法院不能强制变更合同条款，应遵循合同自治原则。"
        }
      ]
    },
    {
      "name": "爭議焦點與裁判要旨",
      "children": [
        {
          "name": "合同条款变更应遵循合同自治原则。"
        },
        {
          "name": "法院不能强制为当事人划定利率标准。"
        },
        {
          "name": "不利解释原则仅适用于条款存在多种解释的情况。"
        },
        {
          "name": "情势变更原则不适用于本案，因保险主要目的是保障。"
        },
        {
          "name": "当事人应协商解决合同履行问题。"
        }
      ]
    },
    {
      "name": "法學見解與實務啟示",
      "children": [
        {
          "name": "本案强调了合同自治原则在民事活动中的重要性。"
        },
        {
          "name": "法院认为，即使由于政策原因导致合同条款无法继续履行，法院也不能强制变更合同内容或为当事人设定新的条款。"
        },
        {
          "name": "合同的变更应由当事人双方协商一致。"
        },
        {
          "name": "本案也澄清了不利解释原则和情势变更原则的适用范围。"
        },
        {
          "name": "不利解释原则仅适用于保险条款存在两种以上合理理解的情况，而情势变更原则的适用需要满足更为严格的条件，包括不可预见性、显失公平或合同目的无法实现等。"
        },
        {
          "name": "本案中，虽然央行停止公布五年期存款利率属于不可预见的情况，但由于保单贷款并非保险合同的主要目的，因此不适用情势变更原则。"
        }
      ]
    }
  ]
}